top_level_implementation.srcs/sources_1/new/simulator.v
`timescale 1ns / 1ps
//////////////////////////////////////////////////////////////////////////////////
// Company:
// Engineer:
//
// Create Date: 08/21/2025 05:30:54 PM
// Design Name:
// Module Name: SIMULATOR
// Project Name:
// Target Devices:
// Tool Versions:
// Description: Parallel DEVS Simulator with FIFO logic
//
// Dependencies:
//
// Revision:
// Revision 0.01 - File Created
// Revision 0.02 - Corrected done signal logic
// Revision 0.03 - Added FIFO logic for input port x
// Additional Comments:
//
//////////////////////////////////////////////////////////////////////////////////

`define WIDTH_PORT 8
`define WIDTH_TIME 8
`define FIFO_DEPTH 5

module simulator (
    input wire [`WIDTH_PORT-1:0] x,
    input wire [`WIDTH_TIME-1:0] at,
    input wire [`WIDTH_TIME-1:0] star,
    input wire clk,
    input wire rst,
    output reg [`WIDTH_PORT-1:0] y,
    output reg [`WIDTH_TIME-1:0] done
);

    // Registros
    reg [`WIDTH_TIME-1:0] tn;
    reg [`WIDTH_TIME-1:0] tL;
    reg [`WIDTH_PORT-1:0] fifo_x [`FIFO_DEPTH-1:0]; // FIFO de 5 elementos
    reg [2:0] fifo_head;
    reg [2:0] fifo_tail;
    reg fifo_empty;
    reg fifo_full;
    reg [`WIDTH_PORT-1:0] fifo_peek_val;

    // Estados para la máquina de estados
    localparam S_IDLE = 2'b00;
    localparam S_EXTERNAL = 2'b01;
    localparam S_INTERNAL = 2'b10;
    reg [1:0] state;
    
    // Contador para los 2 ciclos de las transiciones
    reg [1:0] cycle_count;

    // Lógica secuencial síncrona
    always @(posedge clk or posedge rst) begin
        if (rst) begin
            tn <= 'd0;
            tL <= 'd0;
            y <= 'd0;
            done <= 'd0;
            state <= S_IDLE;
            cycle_count <= 'd0;
            fifo_head <= 3'b0;
            fifo_tail <= 3'b0;
            fifo_empty <= 1'b1;
            fifo_full <= 1'b0;
            fifo_peek_val <= 'd0;
        end else begin
            // Lógica para manejar el FIFO en el estado IDLE
            if (state == S_IDLE) begin
                // Lógica de encolar
                if (x != 'd0 && !fifo_full) begin
                    fifo_x[fifo_tail] <= x;
                    fifo_tail <= fifo_tail + 1;
                    if (fifo_tail + 1 == fifo_head) begin
                        fifo_full <= 1'b1;
                    end
                    fifo_empty <= 1'b0;
                end
            end
            
            case (state)
                S_IDLE: begin
                    done <= 'd0;
                    if (at >= tn && !fifo_empty) begin
                        state <= S_EXTERNAL;
                        cycle_count <= 'd0; 
                        // Lógica de desencolar y "peek" para la transición externa
                        fifo_peek_val <= fifo_x[fifo_head];
                        fifo_head <= fifo_head + 1;
                        if (fifo_head + 1 == fifo_tail) begin
                            fifo_empty <= 1'b1;
                        end
                        fifo_full <= 1'b0;
                    end else if (star != tL) begin
                        state <= S_INTERNAL;
                        cycle_count <= 'd0; 
                    end
                end

                S_EXTERNAL: begin // Lógica para λ (Transición Externa)
                    if (cycle_count == 1) begin // 2 ciclos completos
                        y <= fifo_peek_val;
                        done <= at; 
                        state <= S_IDLE;
                    end else begin
                        cycle_count <= cycle_count + 1;
                    end
                end

                S_INTERNAL: begin // Lógica para δ (Transición Interna)
                    if (cycle_count == 1) begin // 2 ciclos completos
                        tL <= star;
                        tn <= star + 1; 
                        done <= star;
                        state <= S_IDLE;
                    end else begin
                        cycle_count <= cycle_count + 1;
                    end
                end
                default: state <= S_IDLE;
            endcase
        end
    end
endmodule

top_level_implementation.srcs/sources_1/new/coordinator.v
`timescale 1ns / 1ps
//////////////////////////////////////////////////////////////////////////////////
// Company:
// Engineer:
//
// Create Date: 08/21/2025 05:31:21 PM
// Design Name:
// Module Name: coordinator
// Project Name:
// Target Devices:
// Tool Versions:
// Description: Parallel DEVS Coordinator
//
// Dependencies:
//
// Revision:
// Revision 0.01 - File Created
// Additional Comments:
//
//////////////////////////////////////////////////////////////////////////////////

`define WIDTH_TIME 8

module coordinator (
    //Inputs
    input wire [`WIDTH_TIME-1:0] step,
    input wire [`WIDTH_TIME-1:0] done_I,

    input wire clk,
    input wire rst,

    //Outputs
    output reg [`WIDTH_TIME-1:0] at,
    output reg [`WIDTH_TIME-1:0] star,
    output reg [`WIDTH_TIME-1:0] done_O
);

    // Registros internos para la lógica de "espera"
    reg received_done_I;

    always @(posedge clk or posedge rst) begin
        if (rst) begin
            at <= 'd0;
            star <= 'd0;
            done_O <= 'd0;
            received_done_I <= 1'b0;
        end else begin
            // Lógica para el primer wait
            if (step > at) begin
                at <= step;
                received_done_I <= 1'b0; // Resetea el flag al recibir un nuevo step
            end

            // Lógica para el segundo wait
            if (!received_done_I && done_I != 'd0) begin
                received_done_I <= 1'b1;
            end
            
            // Lógica de "todos los done_I han llegado"
            // Suponiendo que 'done_I' es una única entrada
            if (received_done_I) begin
                 star <= done_I;
                 // Asume que done_O se actualiza con el mínimo de los done_I.
                 // Para un solo simulador, done_O = done_I
                 done_O <= done_I;
            end
        end
    end
endmodule

top_level_implementation.srcs/sources_1/new/root_coordinator.v
`timescale 1ns / 1ps
//////////////////////////////////////////////////////////////////////////////////
// Company:
// Engineer:
//
// Create Date: 08/21/2025 05:31:54 PM
// Design Name:
// Module Name: root_coordinator
// Project Name:
// Target Devices:
// Tool Versions:
// Description: Módulo principal que coordina la simulación DEVS.
//
// Dependencies: coordinator.v, simulator.v
//
// Revision:
// Revision 0.01 - File Created
// Revision 0.02 - Corrected step update logic
// Additional Comments:
//
//////////////////////////////////////////////////////////////////////////////////


`define WIDTH_TIME 8
`define WIDTH_PORT 8

module root_coordinator (
    input wire [`WIDTH_TIME-1:0] done,
    input wire clk,
    input wire rst,
    output wire [`WIDTH_TIME-1:0] step
);
    // Asigna el done del coordinador al step, lo que permite el avance del tiempo.
    assign step = done + 1;
endmodule

top_level_implementation.srcs/sources_1/new/top_level.v
`timescale 1ns / 1ps
//////////////////////////////////////////////////////////////////////////////////
// Company:
// Engineer:
//
// Create Date: 08/21/2025 05:32:10 PM
// Design Name:
// Module Name: TOP
// Project Name:
// Target Devices:
// Tool Versions:
// Description: Top-level module for the DEVS system, connecting all sub-modules.
//
// Dependencies: root_coordinator.v, coordinator.v, simulator.v
//
// Revision:
// Revision 0.01 - File Created
// Additional Comments:
//
//////////////////////////////////////////////////////////////////////////////////


module top_level (
    // Inputs from Testbench
    input wire clk,
    input wire rst,
    input wire [`WIDTH_PORT-1:0] x_in_tb,
    
    // Outputs to Testbench
    output wire [`WIDTH_PORT-1:0] y_out_tb,
    output wire [`WIDTH_TIME-1:0] done_out_tb
);

    // Wires for internal connections
    wire [`WIDTH_TIME-1:0] at_w, star_w;
    wire [`WIDTH_TIME-1:0] step_w;
    wire [`WIDTH_TIME-1:0] done_simulator_w;
    wire [`WIDTH_TIME-1:0] done_coordinator_w;

    // Instantiate sub-modules
    root_coordinator dut_root_coord (
        .done(done_coordinator_w),
        .clk(clk),
        .rst(rst),
        .step(step_w)
    );

    coordinator dut_coord (
        .step(step_w),
        .done_I(done_simulator_w),
        .clk(clk),
        .rst(rst),
        .at(at_w),
        .star(star_w),
        .done_O(done_coordinator_w)
    );

    simulator dut_sim (
        .x(x_in_tb),
        .at(at_w),
        .star(star_w),
        .clk(clk),
        .rst(rst),
        .y(y_out_tb),
        .done(done_simulator_w)
    );

    // Connect outputs to testbench
    assign done_out_tb = done_simulator_w;

endmodule

Refactor_top_level.srcs/sim_1/new/testbench.v
`timescale 1ns / 1ps
//////////////////////////////////////////////////////////////////////////////////
// Company:
// Engineer:
//
// Create Date: 08/21/2025 05:32:10 PM
// Design Name:
// Module Name: my_testbench
// Project Name:
// Target Devices:
// Tool Versions:
// Description: Testbench for the DEVS system
//
// Dependencies: TOP.v
//
// Revision:
// Revision 0.01 - File Created
// Additional Comments:
//
//////////////////////////////////////////////////////////////////////////////////


module testbench;
    // Parameters using `define
    `define WIDTH_PORT 8 // Defines the width of the data port
    `define WIDTH_TIME 8 // Defines the width of the time variables
    
    // Signals for top-level module
    reg clk;                       // Clock signal
    reg rst;                       // Reset signal
    reg [`WIDTH_PORT-1:0] x_in_tb; // Input to the DUT
    wire [`WIDTH_PORT-1:0] y_out_tb;   // Output from the DUT
    wire [`WIDTH_TIME-1:0] done_out_tb; // Done signal from the DUT
    
    // Instantiate the top-level module (Design Under Test)
    top_level dut (
        .clk(clk),
        .rst(rst),
        .x_in_tb(x_in_tb),
        .y_out_tb(y_out_tb),
        .done_out_tb(done_out_tb)
    );
    
    // Clock generation (50MHz -> 20ns period)
    initial begin
        clk = 0;
        forever #10 clk = ~clk;
    end
    
    // Test stimulus and waveform dumping
    initial begin
        // Dump all signals to a VCD file for waveform analysis
        $dumpfile("testbench.vcd");
        $dumpvars(0, testbench);
        
        // Monitor key signals in the console
        $monitor("Time=%0t | clk=%0b | rst=%0b | x_in=%0h | y_out=%0h | done=%0d | at=%0d | star=%0d",
                  $time, clk, rst, x_in_tb, y_out_tb, done_out_tb, dut.at_w, dut.star_w);
        
        // --- Simulation sequence ---
        
        $display("-------------------------------------------");
        $display("LOG: Starting Simulation");
        $display("-------------------------------------------");

        // 1. Initial Reset
        $display("LOG: Time %0t | Applying reset...", $time);
        rst = 1;
        x_in_tb = 'd0;
        #20; // Hold reset for one clock cycle
        $display("LOG: Time %0t | Reset released. Starting simulation logic...", $time);
        
        rst = 0;
        #20; // Wait for one cycle to start the simulation process
        $display("LOG: Time %0t | System should now be processing initial state.", $time);
        
        // 2. External event
        $display("LOG: Time %0t | Injecting external event (x_in_tb = 8'hAA).", $time);
        x_in_tb = 8'hAA;
        #40; // Wait for the event to propagate through the system
        
        // 3. Another external event
        $display("LOG: Time %0t | Injecting a new external event (x_in_tb = 8'hBB).", $time);
        x_in_tb = 8'hBB;
        #60; // Wait for propagation
        
        // 4. Clear input and wait for internal transitions
        $display("LOG: Time %0t | Clearing input. Letting the system handle internal transitions.", $time);
        x_in_tb = 'd0;
        #150;
        
        $display("-------------------------------------------");
        $display("LOG: Simulation Finished");
        $display("-------------------------------------------");
        $finish; // End simulation
    end

endmodule

Refactor_top_level.sim/sim_1/behav/xsim/testbench.vcd
$date
   Fri Aug 29 15:26:55 2025
$end

$version
  2025.1.0
  $dumpfile ("testbench.vcd") 
$end

$timescale
  1ps
$end

$scope module testbench $end
$var reg 1 ! clk $end
$var reg 1 " rst $end
$var reg 8 # x_in_tb [7:0] $end
$var wire 8 $ y_out_tb [7:0] $end
$var wire 8 % done_out_tb [7:0] $end
$scope module dut $end
$var wire 1 & clk $end
$var wire 1 ' rst $end
$var wire 8 ( x_in_tb [7:0] $end
$var wire 8 $ y_out_tb [7:0] $end
$var wire 8 % done_out_tb [7:0] $end
$var wire 8 ) at_w [7:0] $end
$var wire 8 * star_w [7:0] $end
$var wire 8 + step_w [7:0] $end
$var wire 8 , done_simulator_w [7:0] $end
$var wire 8 - done_coordinator_w [7:0] $end
$scope module dut_root_coord $end
$var wire 8 - done [7:0] $end
$var wire 1 & clk $end
$var wire 1 ' rst $end
$var wire 8 + step [7:0] $end
$upscope $end
$scope module dut_coord $end
$var wire 8 + step [7:0] $end
$var wire 8 , done_I [7:0] $end
$var wire 1 & clk $end
$var wire 1 ' rst $end
$var reg 8 . at [7:0] $end
$var reg 8 / star [7:0] $end
$var reg 8 0 done_O [7:0] $end
$var reg 1 1 received_done_I $end
$upscope $end
$scope module dut_sim $end
$var wire 8 ( x [7:0] $end
$var wire 8 ) at [7:0] $end
$var wire 8 * star [7:0] $end
$var wire 1 & clk $end
$var wire 1 ' rst $end
$var reg 8 2 y [7:0] $end
$var reg 8 3 done [7:0] $end
$var reg 8 4 tn [7:0] $end
$var reg 8 5 tL [7:0] $end
$var reg 3 6 fifo_head [2:0] $end
$var reg 3 7 fifo_tail [2:0] $end
$var reg 1 8 fifo_empty $end
$var reg 1 9 fifo_full $end
$var reg 8 : fifo_peek_val [7:0] $end
$var reg 2 ; state [1:0] $end
$var reg 2 < cycle_count [1:0] $end
$upscope $end
$upscope $end
$upscope $end
$enddefinitions $end

#0
$dumpvars
0!
1"
b0 #
b0 $
b0 %
0&
1'
b0 (
b0 )
b0 *
b1 +
b0 ,
b0 -
b0 .
b0 /
b0 0
01
b0 2
b0 3
b0 4
b0 5
b0 6
b0 7
18
09
b0 :
b0 ;
b0 <
$end

#10000
1!
1&

#20000
0!
0"
0&
0'

#30000
1!
1&
b1 )
b1 .

#40000
0!
b10101010 #
0&
b10101010 (

#50000
1!
1&
b1 7
08

#60000
0!
0&

#70000
1!
1&
b1 6
b10 7
18
b10101010 :
b1 ;

#80000
0!
b10111011 #
0&
b10111011 (

#90000
1!
1&
b1 <

#100000
0!
0&

#110000
1!
b10101010 $
b1 %
1&
b1 ,
b10101010 2
b1 3
b0 ;

#120000
0!
0&

#130000
1!
b0 %
1&
b0 ,
11
b0 3
b11 7
08

#140000
0!
b0 #
0&
b0 (

#150000
1!
1&
b10 6
b1 ;
b0 <

#160000
0!
0&

#170000
1!
1&
b1 <

#180000
0!
0&

#190000
1!
b1 %
1&
b1 ,
b1 3
b0 ;

#200000
0!
0&

#210000
1!
b0 %
1&
b1 *
b10 +
b0 ,
b1 -
b1 /
b1 0
b0 3
b11 6
18
b10111011 :
b1 ;
b0 <

#220000
0!
0&

#230000
1!
1&
b10 )
b0 *
b1 +
b0 -
b10 .
b0 /
b0 0
01
b1 <

#240000
0!
0&

#250000
1!
b10111011 $
b10 %
1&
b10 ,
b10111011 2
b10 3
b0 ;

#260000
0!
0&

#270000
1!
b0 %
1&
b0 ,
11
b0 3
