Simulation2.0.srcs/sources_1/new/simulator.v
`timescale 1ns / 1ps
//////////////////////////////////////////////////////////////////////////////////
// Company:
// Engineer:
//
// Create Date: 08/21/2025 05:31:04 PM
// Design Name:
// Module Name: simulator
// Project Name:
// Target Devices:
// Tool Versions:
// Description: Parallel DEVS Simulator
//
// Dependencies:
//
// Revision:
// Revision 0.01 - File Created
// Additional Comments:
//
//////////////////////////////////////////////////////////////////////////////////


// Define parameters from specification
`define WP 8 // WIDTH_PORT
`define WT 8 // WIDTH_TIME

module simulator (
    // Inputs
    input wire clk,
    input wire rst,
    input wire [`WP-1:0] x_in,
    input wire [`WT-1:0] at_in,   // External transition time (@)
    input wire [`WT-1:0] star_in, // Internal transition time (*)

    // Outputs
    output reg [`WP-1:0] y_out,
    output reg [`WT-1:0] done_out
);
    // Internal registers for DEVS state and time management
    reg [`WT-1:0] tn; // Time of next internal event
    reg [`WT-1:0] tL; // Time of last event

    // FIFO for input events - simulates event storage
    localparam FIFO_DEPTH = 5;
    reg [`WP-1:0] x_fifo [FIFO_DEPTH-1:0];
    reg [2:0] fifo_write_ptr;
    reg [2:0] fifo_read_ptr;
    reg fifo_empty;
    reg fifo_full;
    
    // FSM for internal delay (e.g., for λ and δ functions)
    localparam S_IDLE = 2'b00;
    localparam S_LAMBDA = 2'b01;
    localparam S_DELTA = 2'b10;
    reg [1:0] state;
    reg [1:0] counter;
    
    // Asynchronous reset and synchronous logic for registers
    always @(posedge clk or posedge rst) begin
        if (rst) begin
            tn <= 0;
            tL <= 0;
            y_out <= 0;
            done_out <= 0;
            state <= S_IDLE;
            counter <= 0;
            fifo_write_ptr <= 0;
            fifo_read_ptr <= 0;
            fifo_empty <= 1'b1;
            fifo_full <= 1'b0;
        end else begin
            // State machine to simulate internal delays and handle transitions
            case (state)
                S_IDLE: begin
                    // Priority: External Transition (@) over Internal Transition (*)
                    if (at_in > tL && at_in <= tn) begin
                        state <= S_LAMBDA;
                        counter <= 0;
                        done_out <= 0; // Clear done until transition is complete
                        
                        // FIFO write logic
                        if (!fifo_full) begin
                            x_fifo[fifo_write_ptr] <= x_in;
                            fifo_write_ptr <= fifo_write_ptr + 1;
                            if (fifo_write_ptr == FIFO_DEPTH - 1) begin
                                fifo_full <= 1'b1;
                            end
                            fifo_empty <= 1'b0;
                        end
                    end
                    // Check for internal transition (*)
                    else if (star_in > tL && star_in == tn) begin
                        state <= S_DELTA;
                        counter <= 0;
                        done_out <= 0; // Clear done until transition is complete
                    end
                end
                
                S_LAMBDA: begin
                    if (counter == 2'd1) begin // Simulates 2-cycle delay for lambda
                        // Lógica de salida λ
                        if (!fifo_empty) begin
                            y_out <= x_fifo[fifo_read_ptr];
                            fifo_read_ptr <= fifo_read_ptr + 1;
                            if (fifo_read_ptr == FIFO_DEPTH - 1) begin
                                fifo_empty <= 1'b1;
                            end
                            fifo_full <= 1'b0;
                        end
                        
                        // Actualizar estado y tiempos después de λ
                        tL <= at_in;
                        done_out <= at_in;
                        state <= S_IDLE;
                    end else begin
                        counter <= counter + 1;
                    end
                end
                
                S_DELTA: begin
                    if (counter == 2'd1) begin // Simulates 2-cycle delay for delta
                        // Lógica de transición δ
                        tL <= star_in;
                        tn <= star_in + 1;
                        done_out <= tn; // Signal completion with the calculated next time
                        state <= S_IDLE;
                    end else begin
                        counter <= counter + 1;
                    end
                end
                
                default: state <= S_IDLE;
            endcase
        end
    end
endmodule

Simulation2.0.srcs/sources_1/new/coordinator.v
`timescale 1ns / 1ps
//////////////////////////////////////////////////////////////////////////////////
// Company:
// Engineer:
//
// Create Date: 08/21/2025 05:31:21 PM
// Design Name:
// Module Name: coordinator
// Project Name:
// Target Devices:
// Tool Versions:
// Description: Parallel DEVS Coordinator
//
// Dependencies:
//
// Revision:
// Revision 0.01 - File Created
// Additional Comments:
//
//////////////////////////////////////////////////////////////////////////////////

`define WT 8 // WIDTH_TIME

module coordinator (
    //Inputs
    input wire clk,
    input wire rst,
    input wire [`WT-1:0] step_in, // Global step time
    input wire [`WT-1:0] done_I_in, // Done signal from the simulator

    //Outputs
    output reg [`WT-1:0] at_out,  // External transition time to simulator
    output reg [`WT-1:0] star_out, // Internal transition time to simulator
    output reg [`WT-1:0] done_O_out
);

    // Internal state machine to manage the simulation cycle
    localparam IDLE      = 2'b00;
    localparam SEND_AT   = 2'b01;
    localparam WAIT_AT   = 2'b10;
    localparam SEND_STAR = 2'b11;
    reg [1:0] state;

    // Internal registers for synchronization and min calculation
    reg [`WT-1:0] min_done;
    reg [`WT-1:0] last_step; // To detect a new step from root_coordinator

    // State and synchronization logic
    always @(posedge clk or posedge rst) begin
        if (rst) begin
            state <= IDLE;
            at_out <= 0;
            star_out <= 0;
            done_O_out <= 0;
            min_done <= -1; // Initialize with max value
            last_step <= 0;
        end else begin
            case (state)
                IDLE: begin
                    if (step_in != last_step) begin // New step from root_coordinator
                        at_out <= step_in;
                        star_out <= 0;
                        state <= SEND_AT;
                        last_step <= step_in;
                    end
                end
                SEND_AT: begin
                    // Wait for done_I from child
                    if (done_I_in == step_in) begin
                        min_done <= done_I_in;
                        state <= WAIT_AT;
                        at_out <= 0; // Clear the signal
                    end
                end
                WAIT_AT: begin
                    star_out <= step_in;
                    state <= SEND_STAR;
                end
                SEND_STAR: begin
                    // Wait for done_I from child
                    if (done_I_in == step_in) begin
                        min_done <= done_I_in;
                        done_O_out <= min_done;
                        state <= IDLE;
                    end
                end
                default: state <= IDLE;
            endcase
        end
    end
endmodule

Simulation DEVS - FPGA/Simulation2.0.srcs/sources_1/new/root_coordinator.v
`timescale 1ns / 1ps
//////////////////////////////////////////////////////////////////////////////////
// Company:
// Engineer:
//
// Create Date: 08/21/2025 05:31:54 PM
// Design Name:
// Module Name: root_coordinator
// Project Name:
// Target Devices:
// Tool Versions:
// Description: Módulo principal que coordina la simulación DEVS.
//
// Dependencies: coordinator.v, simulator.v
//
// Revision:
// Revision 0.01 - File Created
// Revision 0.02 - Corrected step update logic
// Additional Comments:
//
//////////////////////////////////////////////////////////////////////////////////


`define WT 8 // WIDTH_TIME
`define WP 8 // WIDTH_PORT

module root_coordinator (
    // Input
    input wire clk,
    input wire rst,
    input wire [`WP-1:0] x_in_tb,
    output wire [`WT-1:0] step_out // Step signal for the testbench
);
    // Internal signals for module connection
    wire [`WT-1:0] at_w, star_w, done_c_w, done_s_w;
    wire [`WP-1:0] y_w;
    reg [`WT-1:0] next_step_reg;

    // Logic for the next step based on the done signal
    always @(posedge clk or posedge rst) begin
        if (rst) begin
            next_step_reg <= 1; // Start the simulation at time 1
        end else begin
            next_step_reg <= next_step_reg + 1;
        end
    end

    // Coordinator instantiation
    coordinator CM_inst (
        .clk(clk),
        .rst(rst),
        .step_in(next_step_reg),
        .done_I_in(done_s_w), // Assuming a single simulator for simplicity
        .at_out(at_w),
        .star_out(star_w),
        .done_O_out(done_c_w)
    );

    // Simulator instantiation
    simulator AM_inst (
        .clk(clk),
        .rst(rst),
        .x_in(x_in_tb),
        .at_in(at_w),
        .star_in(star_w),
        .y_out(y_w),
        .done_out(done_s_w)
    );

    // Assign the top-level output
    assign step_out = next_step_reg;
endmodule

Simulation2.0.srcs/sim_1/new/testbench.v
`timescale 1ns / 1ps
//////////////////////////////////////////////////////////////////////////////////
// Company:
// Engineer:
//
// Create Date: 08/21/2025 05:32:10 PM
// Design Name:
// Module Name: my_testbench
// Project Name:
// Target Devices:
// Tool Versions:
// Description: Testbench for the DEVS system
//
// Dependencies: root_coordinator.v
//
// Revision:
// Revision 0.01 - File Created
// Additional Comments:
//
//////////////////////////////////////////////////////////////////////////////////

 // Parameters using `define
`define WP 8
`define WT 8

module my_testbench; 
    // Signals
    reg clk;
    reg rst;
    reg [`WP-1:0] x_in_tb;
    wire [`WT-1:0] step_out;
    
    // Instantiate the top-level module
    root_coordinator dut (
        .clk(clk),
        .rst(rst),
        .x_in_tb(x_in_tb),
        .step_out(step_out)
    );
    
    // Clock generation (50MHz -> 20ns period)
    initial begin
        clk = 0;
        forever #10 clk = ~clk;
    end
    
    // Test stimulus and waveform dumping
    initial begin
        // Dump all signals to a VCD file for waveform analysis
        $dumpfile("my_devs_simulation.vcd");
        $dumpvars(0, my_testbench);
        
        // Monitor key signals in the console
        $monitor("Time=%0t | clk=%0b | rst=%0b | x_in_tb=%0h | root_step_out=%0d | coordinator_at=%0d | coordinator_star=%0d | simulator_done=%0d | simulator_y_out=%0h",
                  $time, clk, rst, x_in_tb, dut.step_out, dut.CM_inst.at_out, dut.CM_inst.star_out, dut.AM_inst.done_out, dut.AM_inst.y_out);
        
        // --- Simulation sequence ---
        
        $display("-------------------------------------------");
        $display("LOG: Starting Simulation");
        $display("-------------------------------------------");

        // 1. Initial Reset
        $display("LOG: Time %0t | Applying reset...", $time);
        rst = 1;
        x_in_tb = 0;
        #20; // Hold reset for one clock cycle
        $display("LOG: Time %0t | Reset released. Starting simulation logic...", $time);
        
        rst = 0;
        #20; // Start simulation. root_coordinator will set step_out to 1
        $display("LOG: Time %0t | Coordinator sends first 'at' signal. `at_out` should be 1.", $time);
        
        // 2. External event at time 3 (t=60ns). root_coordinator sends step=1, then receives done from coordinator
        // The coordinator will send at=1 to the simulator
        $display("LOG: Time %0t | External event (x_in_tb = 8'hAA) arrives.", $time);
        x_in_tb = 8'hAA;
        #40; // Wait for the event to propagate. This is where the done signal will come back
        $display("LOG: Time %0t | Waiting for the 'done' signal from the simulator.", $time);
        
        // 3. Another external event at a later time
        // Let's force a new event at a new time step
        // root_coordinator will get the done signal and update its step, then the cycle repeats
        $display("LOG: Time %0t | New external event (x_in_tb = 8'hBB) arrives. Root will update step.", $time);
        x_in_tb = 8'hBB;
        #60; // Wait for propagation
        $display("LOG: Time %0t | Waiting for 'done' from the second external event.", $time);

        // 4. Test internal transition (star)
        // Since we are not simulating internal logic, this is a conceptual test
        // The system will transition on its own based on its internal state (tn)
        // We'll just wait a long time to see it self-propagate
        $display("LOG: Time %0t | Clearing input. Letting the system handle internal transitions.", $time);
        x_in_tb = 8'h00; // Clear input
        #150;
        
        $display("-------------------------------------------");
        $display("LOG: Simulation Finished");
        $display("-------------------------------------------");
        $finish; // End simulation
    end
endmodule

Simulation DEVS - FPGA/Simulation2.0.sim/sim_1/behav/xsim/my_devs_simulation.vcd
$date
   Tue Aug 26 14:21:50 2025
$end

$version
  2025.1.0
  $dumpfile ("my_devs_simulation.vcd") 
$end

$timescale
  1ps
$end

$scope module my_testbench $end
$var reg 1 ! clk $end
$var reg 1 " rst $end
$var reg 8 # x_in_tb [7:0] $end
$var wire 8 $ step_out [7:0] $end
$scope module dut $end
$var wire 1 % clk $end
$var wire 1 & rst $end
$var wire 8 ' x_in_tb [7:0] $end
$var wire 8 $ step_out [7:0] $end
$var wire 8 ( at_w [7:0] $end
$var wire 8 ) star_w [7:0] $end
$var wire 8 * done_c_w [7:0] $end
$var wire 8 + done_s_w [7:0] $end
$var wire 8 , y_w [7:0] $end
$var reg 8 - next_step_reg [7:0] $end
$scope module CM_inst $end
$var wire 1 % clk $end
$var wire 1 & rst $end
$var wire 8 . step_in [7:0] $end
$var wire 8 + done_I_in [7:0] $end
$var reg 8 / at_out [7:0] $end
$var reg 8 0 star_out [7:0] $end
$var reg 8 1 done_O_out [7:0] $end
$var reg 2 2 state [1:0] $end
$var reg 8 3 min_done [7:0] $end
$var reg 8 4 last_step [7:0] $end
$upscope $end
$scope module AM_inst $end
$var wire 1 % clk $end
$var wire 1 & rst $end
$var wire 8 ' x_in [7:0] $end
$var wire 8 ( at_in [7:0] $end
$var wire 8 ) star_in [7:0] $end
$var reg 8 5 y_out [7:0] $end
$var reg 8 6 done_out [7:0] $end
$var reg 8 7 tn [7:0] $end
$var reg 8 8 tL [7:0] $end
$var reg 3 9 fifo_write_ptr [2:0] $end
$var reg 3 : fifo_read_ptr [2:0] $end
$var reg 1 ; fifo_empty $end
$var reg 1 < fifo_full $end
$var reg 2 = state [1:0] $end
$var reg 2 > counter [1:0] $end
$upscope $end
$upscope $end
$upscope $end
$enddefinitions $end

#0
$dumpvars
0!
1"
b0 #
b1 $
0%
1&
b0 '
b0 (
b0 )
b0 *
b0 +
b0 ,
b1 -
b1 .
b0 /
b0 0
b0 1
b0 2
b11111111 3
b0 4
b0 5
b0 6
b0 7
b0 8
b0 9
b0 :
1;
0<
b0 =
b0 >
$end

#10000
1!
1%

#20000
0!
0"
0%
0&

#30000
1!
b10 $
1%
b1 (
b10 -
b10 .
b1 /
b1 2
b1 4

#40000
0!
b10101010 #
0%
b10101010 '

#50000
1!
b11 $
1%
b11 -
b11 .

#60000
0!
0%

#70000
1!
b100 $
1%
b100 -
b100 .

#80000
0!
b10111011 #
0%
b10111011 '

#90000
1!
b101 $
1%
b101 -
b101 .

#100000
0!
0%

#110000
1!
b110 $
1%
b110 -
b110 .

#120000
0!
0%

#130000
1!
b111 $
1%
b111 -
b111 .

#140000
0!
b0 #
0%
b0 '

#150000
1!
b1000 $
1%
b1000 -
b1000 .

#160000
0!
0%

#170000
1!
b1001 $
1%
b1001 -
b1001 .

#180000
0!
0%

#190000
1!
b1010 $
1%
b1010 -
b1010 .

#200000
0!
0%

#210000
1!
b1011 $
1%
b1011 -
b1011 .

#220000
0!
0%

#230000
1!
b1100 $
1%
b1100 -
b1100 .

#240000
0!
0%

#250000
1!
b1101 $
1%
b1101 -
b1101 .

#260000
0!
0%

#270000
1!
b1110 $
1%
b1110 -
b1110 .

