Experimental projects/Simulation DEVS - FPGA/Simulation_DEVS.srcs/sources_1/new/simulator.v
`timescale 1ns / 1ps
//////////////////////////////////////////////////////////////////////////////////
// Company: 
// Engineer: 
// 
// Create Date: 08/12/2025 04:25:12 PM
// Design Name: 
// Module Name: simulator
// Project Name: 
// Target Devices: 
// Tool Versions: 
// Description: 
// 
// Dependencies: 
// 
// Revision:
// Revision 0.01 - File Created
// Additional Comments:
// 
//////////////////////////////////////////////////////////////////////////////////

module simulator (
    input wire clk,
    input wire rst_n,
    input wire at_in,
    input wire q_in,
    output reg done_out
);
    
    // Parámetros de espera
    localparam WAIT_CYCLES_AT = 2'd2; // 2 ciclos para '@'
    localparam WAIT_CYCLES_Q  = 2'd1; // 1 ciclo para 'q'

    // Estados de la máquina
    localparam IDLE    = 2'b00;
    localparam WAIT_AT = 2'b01;
    localparam WAIT_Q  = 2'b10;

    reg [1:0] state, next_state;
    reg [1:0] counter;
    reg next_done_out;
    reg [1:0] next_counter;
    
    // Lógica síncrona
    always @(posedge clk or negedge rst_n) begin
        if (!rst_n) begin
            state <= IDLE;
            counter <= 2'b00;
            done_out <= 1'b0;
        end else begin
            state <= next_state;
            counter <= next_counter;
            done_out <= next_done_out;
        end
    end

    // Lógica combinacional
    always @* begin
        next_state = state;
        next_counter = counter;
        next_done_out = 1'b0; // Valor por defecto

        case (state)
            IDLE: begin
                if (at_in) begin
                    next_state = WAIT_AT;
                    next_counter = 2'b00;
                end else if (q_in) begin
                    next_state = WAIT_Q;
                    next_counter = 2'b00;
                end
            end
            WAIT_AT: begin
                if (counter == WAIT_CYCLES_AT - 1) begin
                    next_done_out = 1'b1;
                    next_state = IDLE;
                end else begin
                    next_counter = counter + 1;
                end
            end
            WAIT_Q: begin
                if (counter == WAIT_CYCLES_Q - 1) begin
                    next_done_out = 1'b1;
                    next_state = IDLE;
                end else begin
                    next_counter = counter + 1;
                end
            end
            default: next_state = IDLE;
        endcase
    end

endmodule

Simulation_DEVS_testbench.srcs/sources_1/new/coordinator.v
`timescale 1ns / 1ps
//////////////////////////////////////////////////////////////////////////////////
// Company: 
// Engineer: 
// 
// Create Date: 08/18/2025 04:56:42 PM
// Design Name: 
// Module Name: coordinator
// Project Name: 
// Target Devices: 
// Tool Versions: 
// Description: 
// 
// Dependencies: 
// 
// Revision:
// Revision 0.01 - File Created
// Additional Comments:
// 
//////////////////////////////////////////////////////////////////////////////////


module coordinator (
    input wire clk,
    input wire rst_n,
    input wire start_in,
    input wire done_in,
    output reg at_out,
    output reg q_out,
    output reg done_out
);

    // Estados de la máquina
    localparam IDLE       = 3'b000;
    localparam SEND_AT    = 3'b001;
    localparam WAIT_DONE1 = 3'b010;
    localparam SEND_Q     = 3'b011;
    localparam WAIT_DONE2 = 3'b100;
    localparam COMPLETE   = 3'b101;
    
    reg [2:0] state, next_state;
    
    // Lógica síncrona
    always @(posedge clk or negedge rst_n) begin
        if (!rst_n) begin
            state <= IDLE;
        end else begin
            state <= next_state;
        end
    end

    // Lógica combinacional
    always @* begin
        next_state = state;
        at_out = 1'b0;
        q_out = 1'b0;
        done_out = 1'b0;
        
        case (state)
            IDLE: begin
                if (start_in) begin
                    next_state = SEND_AT;
                end
            end
            SEND_AT: begin
                at_out = 1'b1;
                next_state = WAIT_DONE1;
            end
            WAIT_DONE1: begin
                if (done_in) begin
                    next_state = SEND_Q;
                end
            end
            SEND_Q: begin
                q_out = 1'b1;
                next_state = WAIT_DONE2;
            end
            WAIT_DONE2: begin
                if (done_in) begin
                    next_state = COMPLETE;
                end
            end
            COMPLETE: begin
                done_out = 1'b1;
                next_state = IDLE;
            end
            default: next_state = IDLE;
        endcase
    end

endmodule

Simulation_DEVS.srcs/sources_1/new/root_coordinator.v
`timescale 1ns / 1ps
//////////////////////////////////////////////////////////////////////////////////
// Company: 
// Engineer: 
// 
// Create Date: 08/12/2025 04:25:41 PM
// Design Name: 
// Module Name: root_coordinator
// Project Name: 
// Target Devices: 
// Tool Versions: 
// Description: 
// 
// Dependencies: 
// 
// Revision:
// Revision 0.01 - File Created
// Additional Comments:
// 
//////////////////////////////////////////////////////////////////////////////////

module root_coordinator (
    input wire clk,
    input wire rst_n,
    input wire start_sim_in,
    output wire done_out
);
    
    // Cables de conexión
    wire at_w, q_w, done_s_w, done_c_w;

    // Instancia del Coordinator
    coordinator CM_inst (
        .clk(clk),
        .rst_n(rst_n),
        .start_in(start_sim_in),
        .done_in(done_s_w),
        .at_out(at_w),
        .q_out(q_w),
        .done_out(done_c_w)
    );

    // Instancia del Simulator
    simulator AM_inst (
        .clk(clk),
        .rst_n(rst_n),
        .at_in(at_w),
        .q_in(q_w),
        .done_out(done_s_w)
    );
    
    assign done_out = done_c_w;

endmodule

Simulation_DEVS.srcs/sim_1/new/root_coordinator_tb.v
`timescale 1ns / 1ps
//////////////////////////////////////////////////////////////////////////////////
// Company: 
// Engineer: 
// 
// Create Date: 08/12/2025 04:26:41 PM
// Design Name: 
// Module Name: root_coordinator_tb
// Project Name: 
// Target Devices: 
// Tool Versions: 
// Description: 
// 
// Dependencies: 
// 
// Revision:
// Revision 0.01 - File Created
// Additional Comments:
// 
//////////////////////////////////////////////////////////////////////////////////

module testbench;
    
    reg clk;
    reg rst_n;
    reg start_sim_in;
    wire done_out;
    
    // Variables para las señales internas
    wire at_w;
    wire q_w;
    wire done_s_w;

    root_coordinator RC_inst (
        .clk(clk),
        .rst_n(rst_n),
        .start_sim_in(start_sim_in),
        .done_out(done_out)
    );
    
    // Conectar las señales internas para poder monitorearlas
    assign at_w = RC_inst.at_w;
    assign q_w = RC_inst.q_w;
    assign done_s_w = RC_inst.done_s_w;

    always #10 clk = ~clk;

    initial begin
        // Generar un archivo de volcado de datos (dump file)
        $dumpfile("testbench.vcd");
        $dumpvars(0, testbench);
        $display("Simulación comenzada a tiempo: %t", $time);

        clk = 1'b0;
        rst_n = 1'b0;

        #20;
        rst_n = 1'b1;

        #20;

        start_sim_in = 1'b1;
        #20;
        start_sim_in = 1'b0;

        #200;
        
        $finish;
    end
endmodule

Experimental projects/Simulation DEVS - FPGA/Simulation_DEVS_testbench.sim/sim_1/behav/xsim/testbench.vcd
$date
   Mon Aug 18 17:43:26 2025
$end

$version
  2025.1.0
  $dumpfile ("testbench.vcd") 
$end

$timescale
  1ps
$end

$scope module testbench $end
$var reg 1 ! clk $end
$var reg 1 " rst_n $end
$var reg 1 # start_sim_in $end
$var wire 1 $ done_out $end
$var wire 1 % at_w $end
$var wire 1 & q_w $end
$var wire 1 ' done_s_w $end
$scope module RC_inst $end
$var wire 1 ( clk $end
$var wire 1 ) rst_n $end
$var wire 1 * start_sim_in $end
$var wire 1 $ done_out $end
$var wire 1 + at_w $end
$var wire 1 , q_w $end
$var wire 1 - done_s_w $end
$var wire 1 . done_c_w $end
$scope module CM_inst $end
$var wire 1 ( clk $end
$var wire 1 ) rst_n $end
$var wire 1 * start_in $end
$var wire 1 - done_in $end
$var reg 1 / at_out $end
$var reg 1 0 q_out $end
$var reg 1 1 done_out $end
$var reg 3 2 state [2:0] $end
$var reg 3 3 next_state [2:0] $end
$upscope $end
$scope module AM_inst $end
$var wire 1 ( clk $end
$var wire 1 ) rst_n $end
$var wire 1 + at_in $end
$var wire 1 , q_in $end
$var reg 1 4 done_out $end
$var reg 2 5 state [1:0] $end
$var reg 2 6 next_state [1:0] $end
$var reg 2 7 counter [1:0] $end
$var reg 1 8 next_done_out $end
$var reg 2 9 next_counter [1:0] $end
$upscope $end
$upscope $end
$upscope $end
$enddefinitions $end

#0
$dumpvars
0!
0"
x#
0$
0%
0&
0'
0(
0)
x*
0+
0,
0-
0.
0/
00
01
b0 2
b0 3
04
b0 5
b0 6
b0 7
08
b0 9
$end

#10000
1!
1(

#20000
0!
1"
0(
1)

#30000
1!
1(

#40000
0!
1#
0(
1*
b1 3

#50000
1!
1%
1(
1+
1/
b1 2
b10 3
b1 6

#60000
0!
0#
0(
0*
1/
b10 3

#70000
1!
0%
1(
0+
0/
b10 2
b1 5
b1 9

#80000
0!
0(

#90000
1!
1(
b0 6
b1 7
18

#100000
0!
0(

#110000
1!
1'
1(
1-
b11 3
14
b0 5
08

#120000
0!
0(

#130000
1!
1&
0'
1(
1,
0-
10
b11 2
b100 3
04
b10 6
b0 9

#140000
0!
0(

#150000
1!
0&
1(
0,
00
b100 2
b10 5
b0 6
b0 7
18

#160000
0!
0(

#170000
1!
1'
1(
1-
b101 3
14
b0 5
08

#180000
0!
0(

#190000
1!
1$
0'
1(
0-
1.
11
b101 2
b0 3
04

#200000
0!
0(

#210000
1!
0$
1(
0.
01
b0 2

